yoloframeuz/__init__.py
yoloframeuz/app.py
yoloframeuz/middleware.py
yoloframeuz/response.py
yoloframeuz-0.1.1.dist-info/METADATA
yoloframeuz-0.1.1.dist-info/WHEEL
yoloframeuz-0.1.1.dist-info/top_level.txt
yoloframeuz-0.1.1.dist-info/RECORD
