Metadata-Version: 2.4
Name: yoloframeuz
Version: 0.1.1
Summary: Test yoloframeuz.
Home-page: https://github.com/murodalidev/yolo-app
Author: Murodali Narzullayev
Author-email: murodalinarzullaevofficial@gmail.com
License: MIT
Classifier: License :: OSI Approved :: MIT License
Classifier: Programming Language :: Python
Classifier: Programming Language :: Python :: 3
Classifier: Programming Language :: Python :: 3.6
Classifier: Programming Language :: Python :: Implementation :: CPython
Classifier: Programming Language :: Python :: Implementation :: PyPy
Requires-Python: >=3.12.0
Requires-Dist: gunicorn==23.0.0
Requires-Dist: parse==1.20.2
Requires-Dist: pytest==8.3.5
Requires-Dist: WebOb==1.8.9
Requires-Dist: requests-wsgi-adapter==0.4.1
Requires-Dist: pytest-cov==6.1.1
Requires-Dist: jinja2==3.1.6
Dynamic: author
Dynamic: author-email
Dynamic: classifier
Dynamic: description
Dynamic: description-content-type
Dynamic: home-page
Dynamic: license
Dynamic: requires-dist
Dynamic: requires-python
Dynamic: summary
